<?xml version="1.0" encoding="utf-8" ?>
<dwsync>
<file name="cam_embed.js" server="tcf.ua.edu//srv/www/shotlogger/" local="129839994560000000" remote="129839994560000000" Dst="2" />
<file name="preload.swf" server="tcf.ua.edu//srv/www/shotlogger/" local="129839994560000000" remote="129839994560000000" Dst="2" />
<file name="swfobject.js" server="tcf.ua.edu//srv/www/shotlogger/" local="129839994560000000" remote="129839994560000000" Dst="2" />
<file name="VLC and Shot Logger.html" server="tcf.ua.edu//srv/www/shotlogger/" local="129839994560000000" remote="129839994560000000" Dst="2" />
<file name="VLC and Shot Logger_config.xml" server="tcf.ua.edu//srv/www/shotlogger/" local="129839994560000000" remote="129839994560000000" Dst="2" />
<file name="VLC and Shot Logger_controller.swf" server="tcf.ua.edu//srv/www/shotlogger/" local="129839994560000000" remote="129839994560000000" Dst="2" />
<file name="VLCcapturing.mp4" server="tcf.ua.edu//srv/www/shotlogger/" local="129839994560000000" remote="129839994560000000" Dst="2" />
<file name="VLCconfiguration.mp4" server="tcf.ua.edu//srv/www/shotlogger/" local="129839994560000000" remote="129839994560000000" Dst="2" />
<file name="VLCinstallation.mp4" server="tcf.ua.edu//srv/www/shotlogger/" local="129839994560000000" remote="129839994560000000" Dst="2" />
<file name="VLCResults.mp4" server="tcf.ua.edu//srv/www/shotlogger/" local="129839994570000000" remote="129839994570000000" Dst="2" />
<file name="index.php" server="tcf.ua.edu//srv/www/shotlogger/" local="130501661580000000" remote="130501661580000000" Dst="2" />
<file name="index_deprecated.html" server="tcf.ua.edu//srv/www/shotlogger/" local="129839994570000000" remote="129839994570000000" Dst="2" />
<file name="vlc-2.0.8-win32.exe" server="tcf.ua.edu//srv/www/shotlogger/" local="130413730160000000" remote="130413730160000000" Dst="2" />
<file name="vlc-2.0.8-win64.exe" server="tcf.ua.edu//srv/www/shotlogger/" local="130413730160000000" remote="130413730160000000" Dst="2" />
<file name="vlc-2.0.8.dmg" server="tcf.ua.edu//srv/www/shotlogger/" local="130413730170000000" remote="130413730170000000" Dst="2" />
<file name="VLC2.0.8Setup_01.jpg" server="tcf.ua.edu//srv/www/shotlogger/" local="130413739900000000" remote="130413739900000000" Dst="2" />
<file name="VLC2.0.8Setup_02.jpg" server="tcf.ua.edu//srv/www/shotlogger/" local="130413739900000000" remote="130413739900000000" Dst="2" />
<file name="VLC2.0.8Setup_03.jpg" server="tcf.ua.edu//srv/www/shotlogger/" local="130413739900000000" remote="130413739900000000" Dst="2" />
<file name="GetVLC.png" server="tcf.ua.edu//srv/www/shotlogger/" local="130414641840000000" remote="130414641840000000" Dst="2" />
<file name="DownloadVLC_deprecated.php" server="tcf.ua.edu//srv/www/shotlogger/" local="130414643740000000" remote="130414643740000000" Dst="2" />
</dwsync>